{
  "title": "! BHK room avialable in Dhanori",
  "description": "Best place for focused study",
  "roomType":"1 BHK",
  "availableFor":"Boys",
  "totalRooms":2,
  "rent":6000,
  "deposit":1000,
  "maintenance":0,
  "brokerage":500,
  "amenities":["wifi","parking","semifurnished","hot water"],

  "address":"pune",
  "city":"pune",
  "area":"dhanori",
  "location": "2nd Floor, Building B",


  "ownerName": "vaibhav",
  "ownerContact": 9090909090,
  "ownerEmail":"vv@gmail.com",
  "isAvailable": true,
  "hasWifi": true,
  "hasChargingPoints": true,
  "hasAC": true,
  "rules": "No talking, maintain silence",
  "openingTime": "2026-04-23T09:00:00+05:30",
  "closingTime": "2026-04-23T21:00:00+05:30",
  "rating": 4.5,
  "createdBy": "admin"
}